maniq/__init__.py
maniq/__main__.py
maniq/cli.py
maniq/core/__init__.py
maniq/core/models.py
maniq/core/resource_monitor.py
maniq/core/tester.py
maniq/i18n/__init__.py
maniq/i18n/translations.py
maniq/i18n/translator.py
maniq/utils/__init__.py
maniq/utils/logging.py
maniq/utils/system_info.py
maniq/utils/text_utils.py
maniq/utils/video_analyzer.py
maniq-3.2.0.dist-info/licenses/LICENSE
maniq-3.2.0.dist-info/METADATA
maniq-3.2.0.dist-info/WHEEL
maniq-3.2.0.dist-info/entry_points.txt
maniq-3.2.0.dist-info/top_level.txt
maniq-3.2.0.dist-info/RECORD
