Metadata-Version: 2.4
Name: maniq
Version: 3.2.0
Summary: Manim Quality Stress Testing Tool
Author-email: MarkHoo <markhoo@foxmail.com>
License-Expression: Apache-2.0
Project-URL: Homepage, https://github.com/MarkHoo/maniq
Project-URL: Repository, https://github.com/MarkHoo/maniq
Project-URL: Issues, https://github.com/MarkHoo/maniq/issues
Keywords: manim,rendering,stress-test,performance,quality
Classifier: Intended Audience :: Developers
Classifier: Operating System :: OS Independent
Classifier: Programming Language :: Python :: 3
Classifier: Programming Language :: Python :: 3.10
Classifier: Programming Language :: Python :: 3.11
Classifier: Programming Language :: Python :: 3.12
Classifier: Programming Language :: Python :: 3.13
Classifier: Programming Language :: Python :: 3.14
Requires-Python: >=3.10
License-File: LICENSE
Requires-Dist: psutil>=7.0.0
Dynamic: license-file
